sudoku_telnet_server/__init__.py
sudoku_telnet_server/server.py
sudoku_telnet_server-0.1.0.dist-info/METADATA
sudoku_telnet_server-0.1.0.dist-info/WHEEL
sudoku_telnet_server-0.1.0.dist-info/entry_points.txt
sudoku_telnet_server-0.1.0.dist-info/top_level.txt
sudoku_telnet_server-0.1.0.dist-info/RECORD
