Metadata-Version: 2.4
Name: sudoku-telnet-server
Version: 0.1.0
Summary: A Sudoku game server built with chuk-protocol-server
Author: Chris Hay
License: MIT
Project-URL: Homepage, https://github.com/chrishayuk/sudoku-telnet-server
Project-URL: Repository, https://github.com/chrishayuk/sudoku-telnet-server
Project-URL: Documentation, https://github.com/chrishayuk/sudoku-telnet-server#readme
Keywords: sudoku,telnet,server,game,websocket
Classifier: Development Status :: 3 - Alpha
Classifier: Intended Audience :: Developers
Classifier: Programming Language :: Python :: 3
Classifier: Programming Language :: Python :: 3.11
Classifier: Programming Language :: Python :: 3.12
Requires-Python: >=3.11
Requires-Dist: chuk-protocol-server>=0.1.0
Provides-Extra: dev
Requires-Dist: pytest>=7.4.0; extra == "dev"
Requires-Dist: pytest-cov>=4.1.0; extra == "dev"
Requires-Dist: pytest-asyncio>=0.21.0; extra == "dev"
Requires-Dist: pytest-watch>=4.2.0; extra == "dev"
Requires-Dist: ruff>=0.1.0; extra == "dev"
Requires-Dist: mypy>=1.4.0; extra == "dev"
Requires-Dist: websockets>=11.0.0; extra == "dev"
Requires-Dist: ipython>=8.14.0; extra == "dev"
